{"is_source_file": false, "format": "", "description": "", "external_files": [], "external_methods": [], "published": [], "classes": [], "methods": [], "calls": [], "search-terms": [], "state": 2, "file_id": 4, "knowledge_revision": 41, "git_revision": "8fdcd6e02b9b3989739242d9644629f207557b1e", "hash": "67d4b3182dfd67da6fc5daddfa77e350", "format-version": 4, "code-base-name": "android-notepad-calculator", "filename": "build.gradle.kts", "revision_history": [{"41": "8fdcd6e02b9b3989739242d9644629f207557b1e"}]}